{"nodes": [{"id": "security_evidence_index", "label": "Security Code, Test, and SBOM Evidence Index", "file_type": "document", "source_file": "security/EVIDENCE_INDEX.md", "source_location": "Code-\u00c4nderungen / Testnachweise / SBOM", "source_url": null, "captured_at": null, "author": null, "contributor": null}], "edges": [{"source": "security_evidence_index", "target": "executive_security_readiness", "relation": "conceptually_related_to", "confidence": "INFERRED", "confidence_score": 0.9, "source_file": "security/EVIDENCE_INDEX.md", "source_location": "Code-\u00c4nderungen / Testnachweise", "weight": 1}], "hyperedges": []}